ohmyfpg-0.3.0.dist-info/METADATA
ohmyfpg-0.3.0.dist-info/WHEEL
ohmyfpg-0.3.0.dist-info/license_files/LICENSE
ohmyfpg/__init__.py
ohmyfpg/ohmyfpg.cpython-310-x86_64-linux-gnu.so
ohmyfpg-0.3.0.dist-info/RECORD
