Metadata-Version: 2.1
Name: ohmyfpg
Version: 0.3.0
Classifier: Programming Language :: Rust
Classifier: Programming Language :: Python :: Implementation :: CPython
Classifier: Programming Language :: Python :: Implementation :: PyPy
License-File: LICENSE
Summary: Oh My Fast Postgres!
Author-email: Lou Marvin Caraig <loumarvincaraig@gmail.com>
Requires-Python: >=3.8
Project-URL: repository, https://github.com/se7entyse7en/ohmyfpg
